AppiumExtensionLibrary/AppiumExtensionLibrary.py
AppiumExtensionLibrary/__init__.py
AppiumExtensionLibrary/errors.py
AppiumExtensionLibrary/version.py
AppiumExtensionLibrary/extension/__init__.py
AppiumExtensionLibrary/extension/_applicationmanagement.py
AppiumExtensionLibrary/extension/_browserextension.py
AppiumExtensionLibrary/extension/_cookiesextension.py
AppiumExtensionLibrary/extension/_elementextension.py
AppiumExtensionLibrary/extension/_selectelement.py
AppiumExtensionLibrary/extension/_waitingextension.py
rf_appiumextensionlibrary-0.9.dist-info/LICENSE
rf_appiumextensionlibrary-0.9.dist-info/METADATA
rf_appiumextensionlibrary-0.9.dist-info/WHEEL
rf_appiumextensionlibrary-0.9.dist-info/top_level.txt
rf_appiumextensionlibrary-0.9.dist-info/RECORD
