Metadata-Version: 2.1
Name: rf-appiumextensionlibrary
Version: 0.9
Summary: serhatbolsu's AppiumLibrary Extension
Home-page: https://github.com/MainSystemDev/rf-appiumextensionlibray
Author: Shiela Buitizon
Author-email: shiela.buitizon@mnltechnology.com
License: MIT License
Platform: any
Classifier: Development Status :: 5 - Production/Stable
Classifier: License :: OSI Approved :: MIT License
Classifier: Operating System :: OS Independent
Classifier: Programming Language :: Python :: 3
Classifier: Topic :: Software Development :: Testing
Classifier: Framework :: Robot Framework
Classifier: Framework :: Robot Framework :: Library
Requires-Dist: pycodestyle
Requires-Dist: robotframework-appiumlibrary (==1.5.0.6)
